Eduponics/__init__.py
Eduponics/ads1x15.py
Eduponics/at24c02.py
Eduponics/bh1750.py
Eduponics/bme280.py
Eduponics/ds1307.py
Eduponics/mcp23017.py
Eduponics/pca9535.py
Eduponics/pcf8563.py
Eduponics/pcf8574.py
Eduponics/qmp6988.py
Eduponics/sht30.py
Eduponics/tds.py
Eduponics/umqttsimple.py
micropython_eduponics-2.0.0.dist-info/LICENSE.md
micropython_eduponics-2.0.0.dist-info/METADATA
micropython_eduponics-2.0.0.dist-info/WHEEL
micropython_eduponics-2.0.0.dist-info/top_level.txt
micropython_eduponics-2.0.0.dist-info/RECORD
