Metadata-Version: 2.1
Name: micropython-eduponics
Version: 2.0.0
Summary: STEMinds Eduponics Mini MicroPython library
Home-page: https://github.com/STEMinds/micropython-eduponics
Download-URL: https://github.com/STEMinds/micropython-eduponics/archive/1.0.8.tar.gz
Author: STEMinds
Author-email: contact@steminds.com
License: MIT
Keywords: STEMinds,MicroPython,uPython,Eduponics-Mini,Eduponics,ESP32,ADS1x15,MCP23017,TDS,pH,bh1750,BME280,DS1307,AT24C02
Classifier: Development Status :: 4 - Beta
Classifier: Intended Audience :: Developers
Classifier: License :: OSI Approved :: MIT License
Classifier: Operating System :: OS Independent
Classifier: Topic :: Software Development
Classifier: Programming Language :: Python :: Implementation :: MicroPython
Classifier: Programming Language :: Python :: 2
Classifier: Programming Language :: Python :: 2.7
Classifier: Programming Language :: Python :: 3
Classifier: Programming Language :: Python :: 3.4
Classifier: Programming Language :: Python :: 3.5
Classifier: Programming Language :: Python :: 3.6
License-File: LICENSE.md
